brfinance/__init__.py
brfinance/backend.py
brfinance/connector.py
brfinance/constants.py
brfinance/http_client.py
brfinance/responses.py
brfinance/utils.py
brfinance-0.0.9.dist-info/METADATA
brfinance-0.0.9.dist-info/WHEEL
brfinance-0.0.9.dist-info/top_level.txt
brfinance-0.0.9.dist-info/RECORD
