Metadata-Version: 2.1
Name: brfinance
Version: 0.0.9
Summary: Biblioteca em Python com o objetivo de facilitar o acesso a dados financeiros periódicos de empresas brasileiras(B3/CVM).
Home-page: https://github.com/eudesrodrigo/brFinance
Author: Eudes Rodrigo Nunes de Oliveira
Author-email: eudesrodrigo@outlook.com
License: UNKNOWN
Download-URL: https://github.com/eudesrodrigo/brFinance/archive/refs/tags/0.0.5.tar.gz
Platform: UNKNOWN
Classifier: License :: OSI Approved :: Apache Software License
Classifier: Programming Language :: Python
Classifier: Programming Language :: Python :: 3.8
Classifier: Operating System :: MacOS :: MacOS X
Classifier: Operating System :: Microsoft :: Windows
Requires-Python: >=3.7.*
Requires-Dist: aiohttp (<4.0.0,>=3.6.2)
Requires-Dist: requests
Requires-Dist: pandas
Requires-Dist: beautifulsoup4
Requires-Dist: lxml
